Assertions/Until/testbench.sv
// Code your design here
`timescale 1ns/1ns

module top;
  
  bit clk;
  
  bit a, b, c;
  
  initial begin
    forever	begin
  	#5 clk = ~clk;
    end
  end	
  
  initial begin
   
    #1;
    
    $display("**************************************************"); 
    $display("Case1:: a and b rise at same time . b and a falls at same time");
    $display("**************************************************"); 
    b = 1;
    a = 1;
    c = 0;
    $display("@%0t: a=%0b, b=%0b, c=%0b", $realtime, a, b, c);
    
    repeat (3) begin 
      @(negedge clk);
      $display("@%0t: a=%0b, b=%0b, c=%0b", $realtime, a, b, c);
    end
    a = 0;
    b = 0;
    c = 1;
    $display("@%0t: a=%0b, b=%0b, c=%0b", $realtime, a, b, c);
    @(negedge clk);
    
    $display("@%0t: a=%0b, b=%0b, c=%0b", $realtime, a, b, c);
    repeat (3) begin 
      @(negedge clk);
      $display("@%0t: a=%0b, b=%0b, c=%0b", $realtime, a, b, c);
    end
    
   
    $display("**************************************************"); 
    $display("Case2::PASS: a and b rise at same time . b falls after a");
    $display("**************************************************"); 
    b = 1;
    a = 1;
    c = 0;
    $display("@%0t: a=%0b, b=%0b, c=%0b", $realtime, a, b, c);
    
    repeat (3) begin 
      @(negedge clk);
      $display("@%0t: a=%0b, b=%0b, c=%0b", $realtime, a, b, c);
    end
    a = 0;
    c = 1;
    $display("@%0t: a=%0b, b=%0b, c=%0b", $realtime, a, b, c);
    @(negedge clk);
    b = 0;
    $display("@%0t: a=%0b, b=%0b, c=%0b", $realtime, a, b, c);
    repeat (3) begin 
      @(negedge clk);
      $display("@%0t: a=%0b, b=%0b, c=%0b", $realtime, a, b, c);
    end
    
    $display("**************************************************"); 
    $display("Case2::FAIL: a and b rise at same time . b falls after a");
    $display("**************************************************"); 
    b = 1;
    a = 1;
    c = 0;
    $display("@%0t: a=%0b, b=%0b, c=%0b", $realtime, a, b, c);
    
    repeat (3) begin 
      @(negedge clk);
      $display("@%0t: a=%0b, b=%0b, c=%0b", $realtime, a, b, c);
    end
    a = 0;
    //c = 0;
    $display("@%0t: a=%0b, b=%0b, c=%0b", $realtime, a, b, c);
    @(negedge clk);
    b = 0;
    c = 1;
    $display("@%0t: a=%0b, b=%0b, c=%0b", $realtime, a, b, c);

    repeat (3) begin 
      @(negedge clk);
      $display("@%0t: a=%0b, b=%0b, c=%0b", $realtime, a, b, c);
    end

    $finish();
  end	
  
  

  property p_until_delayed_end();
    realtime t;
    @(posedge clk) $rose(b||a) |-> b until !a ##0 (1, $display("@%0t: Until Delayed: Ended a=%0b, b=%0b", $realtime, a, b))
    ##1 c;
  endproperty
  
   property p_until();
    realtime t;
     @(posedge clk) $rose(b||a) |-> b until !a ##0 (1, $display("@%0t: Until: Ended a=%0b, b=%0b", $realtime, a, b))
    ##0 c;
  endproperty
  
  property p_until_with_delayed_end();
    realtime t;
    @(posedge clk) $rose(b||a) |-> b until_with !a ##0 (1, $display("@%0t: Until With Delayed: Ended a=%0b, b=%0b", $realtime, a, b))
    ##1 c;
  endproperty
  
  property p_until_with();
    realtime t;
    @(posedge clk) $rose(b||a) |-> b until_with !a ##0 (1, $display("@%0t: Until With: Ended a=%0b, b=%0b", $realtime, a, b))
    ##0 c;
  endproperty


    ASSERT_UNTIL_DELAYED:assert property (p_until_delayed_end()) 
    else
      $error("FAIL ASSERT_UNTIL_DELAYED"); 
          
    ASSERT_UNTIL:assert property (p_until()) 
    else
      $error("FAIL ASSERT_UNTIL"); 
      
    
    ASSERT_UNTIL_WITH_DELAYED: assert property (p_until_with_delayed_end()) 
    else
      $error("FAIL ASSERT_UNTIL_WITH_DELAYED"); 
      
   
    ASSERT_UNTIL_WITH: assert property (p_until_with()) 
    else
      $error("FAIL ASSERT_UNTIL_WITH"); 

   // Dump waves
   initial begin
      $dumpfile("dump.vcd");
      $dumpvars(0, top);
   end   
      
  
endmodule

Assertions/Until/dump.vcd
$date
    Dec 23, 2024  08:03:59
$end
$version
    TOOL:	xmsim	23.09-s001
$end
$timescale
    1 ns
$end

$scope module top $end
$var reg       1 !    clk $end
$var reg       1 "    a $end
$var reg       1 #    b $end
$var reg       1 $    c $end
$upscope $end

$enddefinitions $end
$dumpvars
0!
0"
0#
0$
$end
#1
1#
1"
#5
1!
#10
0!
#15
1!
#20
0!
#25
1!
#30
0!
0"
0#
1$
#35
1!
#40
0!
#45
1!
#50
0!
#55
1!
#60
0!
#65
1!
#70
0!
1#
1"
0$
#75
1!
#80
0!
#85
1!
#90
0!
#95
1!
#100
0!
0"
1$
#105
1!
#110
0!
0#
#115
1!
#120
0!
#125
1!
#130
0!
#135
1!
#140
0!
1#
1"
0$
#145
1!
#150
0!
#155
1!
#160
0!
#165
1!
#170
0!
0"
#175
1!
#180
0!
0#
1$
